napari_multi_channel_surface/__init__.py
napari_multi_channel_surface/_constants.py
napari_multi_channel_surface/_reader.py
napari_multi_channel_surface/_sample_data.py
napari_multi_channel_surface/_version.py
napari_multi_channel_surface/_widget.py
napari_multi_channel_surface/_writer.py
napari_multi_channel_surface/napari.yaml
napari_multi_channel_surface/data/bunny_xyz.vtu
napari_multi_channel_surface-0.0.3.dist-info/licenses/LICENSE
napari_multi_channel_surface-0.0.3.dist-info/METADATA
napari_multi_channel_surface-0.0.3.dist-info/WHEEL
napari_multi_channel_surface-0.0.3.dist-info/entry_points.txt
napari_multi_channel_surface-0.0.3.dist-info/top_level.txt
napari_multi_channel_surface-0.0.3.dist-info/RECORD
