Metadata-Version: 2.4
Name: napari-multi-channel-surface
Version: 0.0.3
Summary: A simple plugin to enable easy interaction with multi-channel surfaces
Author: Judith Lutton
Author-email: judith.e.lutton@gmail.com
License: 
Project-URL: Bug Tracker, https://github.com/judithlutton/napari-multi-channel-surface/issues
Project-URL: Documentation, https://github.com/judithlutton/napari-multi-channel-surface#README.md
Project-URL: Source Code, https://github.com/judithlutton/napari-multi-channel-surface
Project-URL: User Support, https://github.com/judithlutton/napari-multi-channel-surface/issues
Classifier: Development Status :: 2 - Pre-Alpha
Classifier: Framework :: napari
Classifier: Intended Audience :: Developers
Classifier: License :: OSI Approved :: MIT License
Classifier: Operating System :: OS Independent
Classifier: Programming Language :: Python
Classifier: Programming Language :: Python :: 3
Classifier: Programming Language :: Python :: 3 :: Only
Classifier: Programming Language :: Python :: 3.10
Classifier: Programming Language :: Python :: 3.11
Classifier: Programming Language :: Python :: 3.12
Classifier: Programming Language :: Python :: 3.13
Classifier: Topic :: Scientific/Engineering :: Image Processing
Requires-Python: >=3.10
License-File: LICENSE
Requires-Dist: h5py
Requires-Dist: napari
Requires-Dist: numpy
Requires-Dist: magicgui
Requires-Dist: meshio
Requires-Dist: pandas
Requires-Dist: qtpy
Requires-Dist: scikit-image
Provides-Extra: all
Requires-Dist: napari[all]; extra == "all"
Dynamic: license-file
